{
    "file": "chronic-kidney-disease-followup-1.txt-clean.txt",
    "text2summary": {
        "Medication": [
            {
                "text": "Hydroxyzine",
                "code": "5553",
                "cui": "C0020404",
                "tui": "T109",
                "vocab": "RXNORM",
                "polarity": "positive",
                "preferredText": "Hydroxyzine",
                "range": [
                    1586,
                    1597
                ],
                "prob": {
                    "lstm_pred": "MED",
                    "prob": 1.0
                },
                "medFrequencyNumber": [
                    "4",
                    1604,
                    1605
                ],
                "medFrequencyUnit": [
                    "day",
                    1614,
                    1617
                ],
                "medStrengthNum": [
                    "25",
                    1598,
                    1600
                ],
                "medStrengthUnit": [
                    "mg",
                    1601,
                    1603
                ]
            },
            {
                "text": "Hydroxyzine",
                "code": "5553",
                "cui": "C0020404",
                "tui": "T121",
                "vocab": "RXNORM",
                "polarity": "positive",
                "preferredText": "Hydroxyzine",
                "range": [
                    1586,
                    1597
                ],
                "prob": {
                    "lstm_pred": "MED",
                    "prob": 1.0
                },
                "medFrequencyNumber": [
                    "4",
                    1604,
                    1605
                ],
                "medFrequencyUnit": [
                    "day",
                    1614,
                    1617
                ],
                "medStrengthNum": [
                    "25",
                    1598,
                    1600
                ],
                "medStrengthUnit": [
                    "mg",
                    1601,
                    1603
                ]
            },
            {
                "text": "Claritin",
                "code": "203576",
                "cui": "C0701055",
                "tui": "T109",
                "vocab": "RXNORM",
                "polarity": "positive",
                "preferredText": "Claritin",
                "range": [
                    1624,
                    1632
                ],
                "prob": {
                    "lstm_pred": "MED",
                    "prob": 1.0
                },
                "medFrequencyNumber": [],
                "medFrequencyUnit": [
                    "day",
                    1640,
                    1643
                ],
                "medStrengthNum": [
                    "5",
                    1633,
                    1634
                ],
                "medStrengthUnit": [
                    "mg",
                    1635,
                    1637
                ]
            },
            {
                "text": "Claritin",
                "code": "203576",
                "cui": "C0701055",
                "tui": "T121",
                "vocab": "RXNORM",
                "polarity": "positive",
                "preferredText": "Claritin",
                "range": [
                    1624,
                    1632
                ],
                "prob": {
                    "lstm_pred": "MED",
                    "prob": 1.0
                },
                "medFrequencyNumber": [],
                "medFrequencyUnit": [
                    "day",
                    1640,
                    1643
                ],
                "medStrengthNum": [
                    "5",
                    1633,
                    1634
                ],
                "medStrengthUnit": [
                    "mg",
                    1635,
                    1637
                ]
            },
            {
                "text": "Fluoxetine",
                "code": "4493",
                "cui": "C0016365",
                "tui": "T109",
                "vocab": "RXNORM",
                "polarity": "positive",
                "preferredText": "Fluoxetine",
                "range": [
                    1650,
                    1660
                ],
                "prob": {
                    "lstm_pred": "MED",
                    "prob": 1.0
                },
                "medFrequencyNumber": [],
                "medFrequencyUnit": [
                    "day",
                    1669,
                    1672
                ],
                "medStrengthNum": [
                    "20",
                    1661,
                    1663
                ],
                "medStrengthUnit": [
                    "mg",
                    1664,
                    1666
                ]
            },
            {
                "text": "Fluoxetine",
                "code": "4493",
                "cui": "C0016365",
                "tui": "T121",
                "vocab": "RXNORM",
                "polarity": "positive",
                "preferredText": "Fluoxetine",
                "range": [
                    1650,
                    1660
                ],
                "prob": {
                    "lstm_pred": "MED",
                    "prob": 1.0
                },
                "medFrequencyNumber": [],
                "medFrequencyUnit": [
                    "day",
                    1669,
                    1672
                ],
                "medStrengthNum": [
                    "20",
                    1661,
                    1663
                ],
                "medStrengthUnit": [
                    "mg",
                    1664,
                    1666
                ]
            },
            {
                "text": "Ergocalciferol",
                "code": "4018",
                "cui": "C0014695",
                "tui": "T121",
                "vocab": "RXNORM",
                "polarity": "positive",
                "preferredText": "Ergocalciferol",
                "range": [
                    1679,
                    1693
                ],
                "prob": {
                    "lstm_pred": "MED",
                    "prob": 1.0
                },
                "medFrequencyNumber": [],
                "medFrequencyUnit": [
                    "day",
                    1720,
                    1723
                ],
                "medStrengthNum": [],
                "medStrengthUnit": []
            },
            {
                "text": "Ergocalciferol",
                "code": "4018",
                "cui": "C0014695",
                "tui": "T109",
                "vocab": "RXNORM",
                "polarity": "positive",
                "preferredText": "Ergocalciferol",
                "range": [
                    1679,
                    1693
                ],
                "prob": {
                    "lstm_pred": "MED",
                    "prob": 1.0
                },
                "medFrequencyNumber": [],
                "medFrequencyUnit": [
                    "day",
                    1720,
                    1723
                ],
                "medStrengthNum": [],
                "medStrengthUnit": []
            },
            {
                "text": "Protonix",
                "code": "261624",
                "cui": "C0876139",
                "tui": "T121",
                "vocab": "RXNORM",
                "polarity": "positive",
                "preferredText": "Protonix",
                "range": [
                    1730,
                    1738
                ],
                "prob": {
                    "lstm_pred": "MED",
                    "prob": 1.0
                },
                "medFrequencyNumber": [],
                "medFrequencyUnit": [
                    "day",
                    1747,
                    1750
                ],
                "medStrengthNum": [
                    "40",
                    1739,
                    1741
                ],
                "medStrengthUnit": [
                    "mg",
                    1742,
                    1744
                ]
            },
            {
                "text": "Protonix",
                "code": "261624",
                "cui": "C0876139",
                "tui": "T109",
                "vocab": "RXNORM",
                "polarity": "positive",
                "preferredText": "Protonix",
                "range": [
                    1730,
                    1738
                ],
                "prob": {
                    "lstm_pred": "MED",
                    "prob": 1.0
                },
                "medFrequencyNumber": [],
                "medFrequencyUnit": [
                    "day",
                    1747,
                    1750
                ],
                "medStrengthNum": [
                    "40",
                    1739,
                    1741
                ],
                "medStrengthUnit": [
                    "mg",
                    1742,
                    1744
                ]
            },
            {
                "text": "Iron sulfate",
                "code": "24947",
                "cui": "C0060282",
                "tui": "T121",
                "vocab": "RXNORM",
                "polarity": "positive",
                "preferredText": "ferrous sulfate",
                "range": [
                    1757,
                    1769
                ],
                "prob": {
                    "lstm_pred": "MED",
                    "prob": 1.0
                },
                "medFrequencyNumber": [],
                "medFrequencyUnit": [
                    "day",
                    1783,
                    1786
                ],
                "medStrengthNum": [],
                "medStrengthUnit": []
            },
            {
                "text": "Actonel",
                "code": "753143",
                "cui": "C1996201",
                "tui": "T121",
                "vocab": "RXNORM",
                "polarity": "positive",
                "preferredText": "Actonel",
                "range": [
                    1793,
                    1800
                ],
                "prob": {
                    "lstm_pred": "MED",
                    "prob": 1.0
                },
                "medFrequencyNumber": [],
                "medFrequencyUnit": [],
                "medStrengthNum": [
                    "35",
                    1801,
                    1803
                ],
                "medStrengthUnit": [
                    "mg",
                    1804,
                    1806
                ]
            },
            {
                "text": "Actonel",
                "code": "753143",
                "cui": "C1996201",
                "tui": "T109",
                "vocab": "RXNORM",
                "polarity": "positive",
                "preferredText": "Actonel",
                "range": [
                    1793,
                    1800
                ],
                "prob": {
                    "lstm_pred": "MED",
                    "prob": 1.0
                },
                "medFrequencyNumber": [],
                "medFrequencyUnit": [],
                "medStrengthNum": [
                    "35",
                    1801,
                    1803
                ],
                "medStrengthUnit": [
                    "mg",
                    1804,
                    1806
                ]
            },
            {
                "text": "Zantac 150",
                "code": "220992",
                "cui": "C0724451",
                "tui": "T109",
                "vocab": "RXNORM",
                "polarity": "positive",
                "preferredText": "Zantac 150",
                "range": [
                    1825,
                    1835
                ],
                "prob": {
                    "lstm_pred": "MED",
                    "prob": 1.0
                },
                "medFrequencyNumber": [],
                "medFrequencyUnit": [
                    "day"
                ],
                "medStrengthNum": [
                    "150",
                    1832,
                    1835
                ],
                "medStrengthUnit": [
                    "mg",
                    1836,
                    1838
                ]
            },
            {
                "text": "Zantac 150",
                "code": "220992",
                "cui": "C0724451",
                "tui": "T121",
                "vocab": "RXNORM",
                "polarity": "positive",
                "preferredText": "Zantac 150",
                "range": [
                    1825,
                    1835
                ],
                "prob": {
                    "lstm_pred": "MED",
                    "prob": 1.0
                },
                "medFrequencyNumber": [],
                "medFrequencyUnit": [
                    "day"
                ],
                "medStrengthNum": [
                    "150",
                    1832,
                    1835
                ],
                "medStrengthUnit": [
                    "mg",
                    1836,
                    1838
                ]
            },
            {
                "text": "Calcium carbonate",
                "code": "1897",
                "cui": "C0006681",
                "tui": "T121",
                "vocab": "RXNORM",
                "polarity": "positive",
                "preferredText": "Calcium Carbonate",
                "range": [
                    1852,
                    1869
                ],
                "prob": {
                    "lstm_pred": "MED",
                    "prob": 1.0
                },
                "medFrequencyNumber": [
                    "3",
                    1877,
                    1878
                ],
                "medFrequencyUnit": [
                    "day",
                    1887,
                    1890
                ],
                "medStrengthNum": [
                    "500",
                    1870,
                    1873
                ],
                "medStrengthUnit": [
                    "mg",
                    1874,
                    1876
                ]
            },
            {
                "text": "NovoLog",
                "code": "284810",
                "cui": "C0939412",
                "tui": "T121",
                "vocab": "RXNORM",
                "polarity": "positive",
                "preferredText": "NovoLog",
                "range": [
                    1898,
                    1905
                ],
                "prob": {
                    "lstm_pred": "MED",
                    "prob": 1.0
                },
                "medFrequencyNumber": [],
                "medFrequencyUnit": [
                    "day"
                ],
                "medStrengthNum": [
                    "30",
                    1937,
                    1939
                ],
                "medStrengthUnit": [
                    "units",
                    1940,
                    1945
                ]
            },
            {
                "text": "insulin",
                "code": null,
                "cui": null,
                "tui": null,
                "vocab": null,
                "polarity": "positive",
                "preferredText": null,
                "range": [
                    1906,
                    1913
                ],
                "prob": {
                    "MED": 0.983
                },
                "medFrequencyNumber": [],
                "medFrequencyUnit": [],
                "medStrengthNum": [],
                "medStrengthUnit": []
            },
            {
                "text": "insulin",
                "code": null,
                "cui": null,
                "tui": null,
                "vocab": null,
                "polarity": "positive",
                "preferredText": null,
                "range": [
                    1918,
                    1925
                ],
                "prob": {
                    "MED": 0.947
                },
                "medFrequencyNumber": [],
                "medFrequencyUnit": [],
                "medStrengthNum": [],
                "medStrengthUnit": []
            },
            {
                "text": "insulin",
                "code": null,
                "cui": null,
                "tui": null,
                "vocab": null,
                "polarity": "positive",
                "preferredText": null,
                "range": [
                    1949,
                    1956
                ],
                "prob": {
                    "MED": 0.921
                },
                "medFrequencyNumber": [],
                "medFrequencyUnit": [],
                "medStrengthNum": [],
                "medStrengthUnit": []
            },
            {
                "text": "Zocor",
                "code": "196503",
                "cui": "C0678181",
                "tui": "T109",
                "vocab": "RXNORM",
                "polarity": "positive",
                "preferredText": "Zocor",
                "range": [
                    1970,
                    1975
                ],
                "prob": {
                    "lstm_pred": "MED",
                    "prob": 1.0
                },
                "medFrequencyNumber": [],
                "medFrequencyUnit": [
                    "day",
                    1984,
                    1987
                ],
                "medStrengthNum": [
                    "40",
                    1976,
                    1978
                ],
                "medStrengthUnit": [
                    "mg",
                    1979,
                    1981
                ]
            },
            {
                "text": "Zocor",
                "code": "196503",
                "cui": "C0678181",
                "tui": "T121",
                "vocab": "RXNORM",
                "polarity": "positive",
                "preferredText": "Zocor",
                "range": [
                    1970,
                    1975
                ],
                "prob": {
                    "lstm_pred": "MED",
                    "prob": 1.0
                },
                "medFrequencyNumber": [],
                "medFrequencyUnit": [
                    "day",
                    1984,
                    1987
                ],
                "medStrengthNum": [
                    "40",
                    1976,
                    1978
                ],
                "medStrengthUnit": [
                    "mg",
                    1979,
                    1981
                ]
            },
            {
                "text": "Valsartan",
                "code": "69749",
                "cui": "C0216784",
                "tui": "T121",
                "vocab": "RXNORM",
                "polarity": "positive",
                "preferredText": "valsartan",
                "range": [
                    1995,
                    2004
                ],
                "prob": {
                    "lstm_pred": "MED",
                    "prob": 1.0
                },
                "medFrequencyNumber": [],
                "medFrequencyUnit": [
                    "day"
                ],
                "medStrengthNum": [
                    "80",
                    2005,
                    2007
                ],
                "medStrengthUnit": [
                    "mg",
                    2008,
                    2010
                ]
            },
            {
                "text": "Valsartan",
                "code": "69749",
                "cui": "C0216784",
                "tui": "T109",
                "vocab": "RXNORM",
                "polarity": "positive",
                "preferredText": "valsartan",
                "range": [
                    1995,
                    2004
                ],
                "prob": {
                    "lstm_pred": "MED",
                    "prob": 1.0
                },
                "medFrequencyNumber": [],
                "medFrequencyUnit": [
                    "day"
                ],
                "medStrengthNum": [
                    "80",
                    2005,
                    2007
                ],
                "medStrengthUnit": [
                    "mg",
                    2008,
                    2010
                ]
            },
            {
                "text": "Amlodipine",
                "code": "17767",
                "cui": "C0051696",
                "tui": "T121",
                "vocab": "RXNORM",
                "polarity": "positive",
                "preferredText": "Amlodipine",
                "range": [
                    2024,
                    2034
                ],
                "prob": {
                    "lstm_pred": "MED",
                    "prob": 1.0
                },
                "medFrequencyNumber": [],
                "medFrequencyUnit": [
                    "day",
                    2042,
                    2045
                ],
                "medStrengthNum": [
                    "5",
                    2035,
                    2036
                ],
                "medStrengthUnit": [
                    "mg",
                    2037,
                    2039
                ]
            },
            {
                "text": "Amlodipine",
                "code": "17767",
                "cui": "C0051696",
                "tui": "T109",
                "vocab": "RXNORM",
                "polarity": "positive",
                "preferredText": "Amlodipine",
                "range": [
                    2024,
                    2034
                ],
                "prob": {
                    "lstm_pred": "MED",
                    "prob": 1.0
                },
                "medFrequencyNumber": [],
                "medFrequencyUnit": [
                    "day",
                    2042,
                    2045
                ],
                "medStrengthNum": [
                    "5",
                    2035,
                    2036
                ],
                "medStrengthUnit": [
                    "mg",
                    2037,
                    2039
                ]
            },
            {
                "text": "Plavix",
                "code": "174742",
                "cui": "C0633084",
                "tui": "T109",
                "vocab": "RXNORM",
                "polarity": "positive",
                "preferredText": "Plavix",
                "range": [
                    2053,
                    2059
                ],
                "prob": {
                    "lstm_pred": "MED",
                    "prob": 1.0
                },
                "medFrequencyNumber": [],
                "medFrequencyUnit": [
                    "day",
                    2068,
                    2071
                ],
                "medStrengthNum": [
                    "75",
                    2060,
                    2062
                ],
                "medStrengthUnit": [
                    "mg",
                    2063,
                    2065
                ]
            },
            {
                "text": "Plavix",
                "code": "174742",
                "cui": "C0633084",
                "tui": "T121",
                "vocab": "RXNORM",
                "polarity": "positive",
                "preferredText": "Plavix",
                "range": [
                    2053,
                    2059
                ],
                "prob": {
                    "lstm_pred": "MED",
                    "prob": 1.0
                },
                "medFrequencyNumber": [],
                "medFrequencyUnit": [
                    "day",
                    2068,
                    2071
                ],
                "medStrengthNum": [
                    "75",
                    2060,
                    2062
                ],
                "medStrengthUnit": [
                    "mg",
                    2063,
                    2065
                ]
            },
            {
                "text": "Aspirin",
                "code": "1191",
                "cui": "C0004057",
                "tui": "T121",
                "vocab": "RXNORM",
                "polarity": "positive",
                "preferredText": "Aspirin",
                "range": [
                    2079,
                    2086
                ],
                "prob": {
                    "lstm_pred": "MED",
                    "prob": 1.0
                },
                "medFrequencyNumber": [],
                "medFrequencyUnit": [
                    "day",
                    2095,
                    2098
                ],
                "medStrengthNum": [
                    "81",
                    2087,
                    2089
                ],
                "medStrengthUnit": [
                    "mg",
                    2090,
                    2092
                ]
            },
            {
                "text": "Aspirin",
                "code": "1191",
                "cui": "C0004057",
                "tui": "T109",
                "vocab": "RXNORM",
                "polarity": "positive",
                "preferredText": "Aspirin",
                "range": [
                    2079,
                    2086
                ],
                "prob": {
                    "lstm_pred": "MED",
                    "prob": 1.0
                },
                "medFrequencyNumber": [],
                "medFrequencyUnit": [
                    "day",
                    2095,
                    2098
                ],
                "medStrengthNum": [
                    "81",
                    2087,
                    2089
                ],
                "medStrengthUnit": [
                    "mg",
                    2090,
                    2092
                ]
            },
            {
                "text": "Lasix",
                "code": "202991",
                "cui": "C0699992",
                "tui": "T121",
                "vocab": "RXNORM",
                "polarity": "positive",
                "preferredText": "Lasix",
                "range": [
                    2106,
                    2111
                ],
                "prob": {
                    "lstm_pred": "MED",
                    "prob": 1.0
                },
                "medFrequencyNumber": [],
                "medFrequencyUnit": [
                    "day",
                    2120,
                    2123
                ],
                "medStrengthNum": [
                    "20",
                    2112,
                    2114
                ],
                "medStrengthUnit": [
                    "mg",
                    2115,
                    2117
                ]
            },
            {
                "text": "Lasix",
                "code": "202991",
                "cui": "C0699992",
                "tui": "T109",
                "vocab": "RXNORM",
                "polarity": "positive",
                "preferredText": "Lasix",
                "range": [
                    2106,
                    2111
                ],
                "prob": {
                    "lstm_pred": "MED",
                    "prob": 1.0
                },
                "medFrequencyNumber": [],
                "medFrequencyUnit": [
                    "day",
                    2120,
                    2123
                ],
                "medStrengthNum": [
                    "20",
                    2112,
                    2114
                ],
                "medStrengthUnit": [
                    "mg",
                    2115,
                    2117
                ]
            },
            {
                "text": "Levothyroxine",
                "code": null,
                "cui": null,
                "tui": null,
                "vocab": null,
                "polarity": "positive",
                "preferredText": null,
                "range": [
                    2131,
                    2144
                ],
                "prob": {
                    "MED": 0.949
                },
                "medFrequencyNumber": [],
                "medFrequencyUnit": [],
                "medStrengthNum": [],
                "medStrengthUnit": []
            }
        ],
        "Allergy": [],
        "Lab": [
            {
                "code": "LP32534-7",
                "cui": "C0017725",
                "tui": "T034",
                "vocab": "LNC",
                "polarity": "positive",
                "text": "glucose",
                "preferredText": "GLUCOSE",
                "range": [
                    650,
                    657
                ]
            },
            {
                "code": "",
                "cui": "C0518015",
                "tui": "T034",
                "vocab": "LNC",
                "polarity": "positive",
                "text": "hemoglobin",
                "preferredText": "HEMOGLOBIN DETERMINATION (PROCEDURE)",
                "range": [
                    4243,
                    4253
                ]
            },
            {
                "code": "LP32067-8",
                "cui": "C0019046",
                "tui": "T034",
                "vocab": "LNC",
                "polarity": "positive",
                "text": "hemoglobin",
                "preferredText": "HEMOGLOBIN",
                "range": [
                    4243,
                    4253
                ]
            }
        ],
        "DiseaseDisorder": [
            {
                "text": "Type 1 diabetes mellitus",
                "range": [
                    22,
                    46
                ],
                "polarity": "positive",
                "lstm_prob": 1.0,
                "code": "46635009",
                "cui": "C0011854",
                "tui": "T047",
                "vocab": "SNOMEDCT_US",
                "preferredText": "Diabetes Mellitus, Insulin-Dependent"
            },
            {
                "text": "Chronic kidney disease",
                "range": [
                    77,
                    99
                ],
                "polarity": "positive",
                "lstm_prob": 1.0,
                "code": "709044004",
                "cui": "C1561643",
                "tui": "T047",
                "vocab": "SNOMEDCT_US",
                "preferredText": "Chronic Kidney Diseases"
            },
            {
                "text": "stage III",
                "range": [
                    101,
                    110
                ],
                "lstm_prob": 1.0,
                "attributes": {
                    "polarity": "positive"
                },
                "polarity": "positive",
                "umlsConcept": []
            },
            {
                "text": "Sweet syndrome",
                "range": [
                    117,
                    131
                ],
                "polarity": "positive",
                "lstm_prob": 1.0,
                "code": "84625002",
                "cui": "C0085077",
                "tui": "T047",
                "vocab": "SNOMEDCT_US",
                "preferredText": "Sweet Syndrome"
            },
            {
                "text": "Hypertension",
                "range": [
                    138,
                    150
                ],
                "polarity": "positive",
                "lstm_prob": 1.0,
                "code": "38341003",
                "cui": "C0020538",
                "tui": "T047",
                "vocab": "SNOMEDCT_US",
                "preferredText": "Hypertensive disease"
            },
            {
                "text": "Dyslipidemia",
                "range": [
                    157,
                    169
                ],
                "polarity": "positive",
                "lstm_prob": 1.0,
                "code": "370992007",
                "cui": "C0242339",
                "tui": "T047",
                "vocab": "SNOMEDCT_US",
                "preferredText": "Dyslipidemias"
            },
            {
                "text": "Osteoporosis",
                "range": [
                    176,
                    188
                ],
                "polarity": "positive",
                "lstm_prob": 1.0,
                "code": "64859006",
                "cui": "C0029456",
                "tui": "T047",
                "vocab": "SNOMEDCT_US",
                "preferredText": "Osteoporosis"
            },
            {
                "text": "Anemia",
                "range": [
                    195,
                    201
                ],
                "polarity": "positive",
                "lstm_prob": 1.0,
                "code": "271737000",
                "cui": "C0002871",
                "tui": "T047",
                "vocab": "SNOMEDCT_US",
                "preferredText": "Anemia"
            },
            {
                "text": "25-hydroxy-vitamin D deficiency",
                "range": [
                    210,
                    241
                ],
                "polarity": "positive",
                "lstm_prob": 1.0,
                "code": "34713006",
                "cui": "C0042870",
                "tui": "T047",
                "vocab": "SNOMEDCT_US",
                "preferredText": "Vitamin D Deficiency"
            },
            {
                "text": "Peripheral neuropathy",
                "range": [
                    248,
                    269
                ],
                "polarity": "positive",
                "lstm_prob": 1.0,
                "code": "302226006",
                "cui": "C0031117",
                "tui": "T047",
                "vocab": "SNOMEDCT_US",
                "preferredText": "Peripheral Neuropathy"
            },
            {
                "text": "feet",
                "range": [
                    294,
                    298
                ],
                "lstm_prob": 1.0,
                "attributes": {
                    "polarity": "positive"
                },
                "polarity": "positive",
                "umlsConcept": []
            },
            {
                "text": "Hypothyroidism",
                "range": [
                    306,
                    320
                ],
                "polarity": "positive",
                "lstm_prob": 1.0,
                "code": "40930008",
                "cui": "C0020676",
                "tui": "T047",
                "vocab": "SNOMEDCT_US",
                "preferredText": "Hypothyroidism"
            },
            {
                "text": "Diabetic retinopathy",
                "range": [
                    328,
                    348
                ],
                "polarity": "positive",
                "lstm_prob": 1.0,
                "code": "4855003",
                "cui": "C0011884",
                "tui": "T047",
                "vocab": "SNOMEDCT_US",
                "preferredText": "Diabetic Retinopathy"
            },
            {
                "text": "diabetes",
                "range": [
                    467,
                    475
                ],
                "polarity": "positive",
                "lstm_prob": 1.0,
                "code": "73211009",
                "cui": "C0011849",
                "tui": "T047",
                "vocab": "SNOMEDCT_US",
                "preferredText": "Diabetes Mellitus"
            },
            {
                "text": "kidney disease",
                "range": [
                    480,
                    494
                ],
                "polarity": "positive",
                "lstm_prob": 1.0,
                "code": "90708001",
                "cui": "C0022658",
                "tui": "T047",
                "vocab": "SNOMEDCT_US",
                "preferredText": "Kidney Diseases"
            },
            {
                "text": "variability",
                "range": [
                    631,
                    642
                ],
                "lstm_prob": 1.0,
                "attributes": {
                    "polarity": "positive"
                },
                "polarity": "positive",
                "umlsConcept": []
            },
            {
                "text": "glucose control",
                "range": [
                    650,
                    665
                ],
                "lstm_prob": 1.0,
                "attributes": {
                    "polarity": "positive"
                },
                "polarity": "positive",
                "umlsConcept": []
            },
            {
                "text": "upper",
                "range": [
                    688,
                    693
                ],
                "lstm_prob": 1.0,
                "attributes": {
                    "polarity": "positive"
                },
                "polarity": "positive",
                "umlsConcept": []
            },
            {
                "text": "lower respiratory",
                "range": [
                    698,
                    715
                ],
                "lstm_prob": 1.0,
                "attributes": {
                    "polarity": "positive"
                },
                "polarity": "positive",
                "umlsConcept": []
            },
            {
                "text": "control",
                "range": [
                    1379,
                    1386
                ],
                "lstm_prob": 1.0,
                "attributes": {
                    "polarity": "positive"
                },
                "polarity": "positive",
                "umlsConcept": []
            },
            {
                "text": "nausea",
                "range": [
                    2302,
                    2308
                ],
                "lstm_prob": 1.0,
                "attributes": {
                    "polarity": "positive"
                },
                "polarity": "positive",
                "umlsConcept": []
            },
            {
                "text": "constipation",
                "range": [
                    2320,
                    2332
                ],
                "lstm_prob": 1.0,
                "attributes": {
                    "polarity": "positive"
                },
                "polarity": "positive",
                "umlsConcept": []
            },
            {
                "text": "hesitancy",
                "range": [
                    2478,
                    2487
                ],
                "lstm_prob": 1.0,
                "attributes": {
                    "polarity": "positive"
                },
                "polarity": "positive",
                "umlsConcept": []
            },
            {
                "text": "battery",
                "range": [
                    4380,
                    4387
                ],
                "polarity": "positive",
                "lstm_prob": 1.0,
                "code": "50084004",
                "cui": "C0542351",
                "tui": "T037",
                "vocab": "SNOMEDCT_US",
                "preferredText": "Battery (assault)"
            }
        ]
    },
    "medication_uncertainty": {
        "average_entropy": 0.011,
        "uncertain_count": 5,
        "narrow_band_ratio": 0.005,
        "uncertain_tokens": {
            "NA": [
                [
                    0.583,
                    "insulin",
                    [
                        48,
                        55
                    ]
                ],
                [
                    0.63,
                    "glucose",
                    [
                        650,
                        657
                    ]
                ],
                [
                    0.626,
                    "A1C",
                    [
                        4254,
                        4257
                    ]
                ]
            ],
            "MED": [
                [
                    0.656,
                    "glucose",
                    [
                        1371,
                        1378
                    ]
                ],
                [
                    0.511,
                    "insulin",
                    [
                        4319,
                        4326
                    ]
                ]
            ]
        },
        "narrow_band_width": 0.2
    },
    "problem_uncertainty": {
        "majority": [
            {
                "DIAGNOSIS": [
                    "Type",
                    [
                        22,
                        26
                    ]
                ]
            },
            {
                "DIAGNOSIS": [
                    "1",
                    [
                        27,
                        28
                    ]
                ]
            },
            {
                "DIAGNOSIS": [
                    "diabetes",
                    [
                        29,
                        37
                    ]
                ]
            },
            {
                "DIAGNOSIS": [
                    "mellitus",
                    [
                        38,
                        46
                    ]
                ]
            },
            {
                "DIAGNOSIS": [
                    "Chronic",
                    [
                        77,
                        84
                    ]
                ]
            },
            {
                "DIAGNOSIS": [
                    "kidney",
                    [
                        85,
                        91
                    ]
                ]
            },
            {
                "DIAGNOSIS": [
                    "disease",
                    [
                        92,
                        99
                    ]
                ]
            },
            {
                "DIAGNOSIS": [
                    ",",
                    [
                        99,
                        100
                    ]
                ]
            },
            {
                "DIAGNOSIS": [
                    "stage",
                    [
                        101,
                        106
                    ]
                ]
            },
            {
                "DIAGNOSIS": [
                    "III",
                    [
                        107,
                        110
                    ]
                ]
            },
            {
                "DIAGNOSIS": [
                    "Sweet",
                    [
                        117,
                        122
                    ]
                ]
            },
            {
                "DIAGNOSIS": [
                    "syndrome",
                    [
                        123,
                        131
                    ]
                ]
            },
            {
                "DIAGNOSIS": [
                    "Hypertension",
                    [
                        138,
                        150
                    ]
                ]
            },
            {
                "DIAGNOSIS": [
                    "Dyslipidemia",
                    [
                        157,
                        169
                    ]
                ]
            },
            {
                "DIAGNOSIS": [
                    "Osteoporosis",
                    [
                        176,
                        188
                    ]
                ]
            },
            {
                "DIAGNOSIS": [
                    "Anemia",
                    [
                        195,
                        201
                    ]
                ]
            },
            {
                "DIAGNOSIS": [
                    "25-hydroxy-vitamin",
                    [
                        210,
                        228
                    ]
                ]
            },
            {
                "DIAGNOSIS": [
                    "D",
                    [
                        229,
                        230
                    ]
                ]
            },
            {
                "DIAGNOSIS": [
                    "deficiency",
                    [
                        231,
                        241
                    ]
                ]
            },
            {
                "DIAGNOSIS": [
                    "Peripheral",
                    [
                        248,
                        258
                    ]
                ]
            },
            {
                "DIAGNOSIS": [
                    "neuropathy",
                    [
                        259,
                        269
                    ]
                ]
            },
            {
                "PROBLEM": [
                    "feet",
                    [
                        294,
                        298
                    ]
                ]
            },
            {
                "DIAGNOSIS": [
                    "Hypothyroidism",
                    [
                        306,
                        320
                    ]
                ]
            },
            {
                "DIAGNOSIS": [
                    "Diabetic",
                    [
                        328,
                        336
                    ]
                ]
            },
            {
                "DIAGNOSIS": [
                    "retinopathy",
                    [
                        337,
                        348
                    ]
                ]
            },
            {
                "DIAGNOSIS": [
                    "diabetes",
                    [
                        467,
                        475
                    ]
                ]
            },
            {
                "DIAGNOSIS": [
                    "kidney",
                    [
                        480,
                        486
                    ]
                ]
            },
            {
                "DIAGNOSIS": [
                    "disease",
                    [
                        487,
                        494
                    ]
                ]
            },
            {
                "DIAGNOSIS": [
                    "management",
                    [
                        495,
                        505
                    ]
                ]
            },
            {
                "DIAGNOSIS": [
                    "variability",
                    [
                        631,
                        642
                    ]
                ]
            },
            {
                "PROBLEM": [
                    "glucose",
                    [
                        650,
                        657
                    ]
                ]
            },
            {
                "DIAGNOSIS": [
                    "control",
                    [
                        658,
                        665
                    ]
                ]
            },
            {
                "PROBLEM": [
                    "upper",
                    [
                        688,
                        693
                    ]
                ]
            },
            {
                "PROBLEM": [
                    "lower",
                    [
                        698,
                        703
                    ]
                ]
            },
            {
                "DIAGNOSIS": [
                    "respiratory",
                    [
                        704,
                        715
                    ]
                ]
            },
            {
                "DIAGNOSIS": [
                    "illnesses",
                    [
                        716,
                        725
                    ]
                ]
            },
            {
                "DIAGNOSIS": [
                    "difficulties",
                    [
                        865,
                        877
                    ]
                ]
            },
            {
                "DIAGNOSIS": [
                    "control",
                    [
                        1379,
                        1386
                    ]
                ]
            },
            {
                "PROBLEM": [
                    "nausea",
                    [
                        2302,
                        2308
                    ]
                ]
            },
            {
                "PROBLEM": [
                    "constipation",
                    [
                        2320,
                        2332
                    ]
                ]
            },
            {
                "DIAGNOSIS": [
                    "hesitancy",
                    [
                        2478,
                        2487
                    ]
                ]
            },
            {
                "PROBLEM": [
                    "battery",
                    [
                        4380,
                        4387
                    ]
                ]
            }
        ],
        "weighted": [
            {
                "DIAGNOSIS": [
                    0.959,
                    "Type",
                    [
                        22,
                        26
                    ]
                ]
            },
            {
                "DIAGNOSIS": [
                    0.934,
                    "1",
                    [
                        27,
                        28
                    ]
                ]
            },
            {
                "DIAGNOSIS": [
                    0.976,
                    "diabetes",
                    [
                        29,
                        37
                    ]
                ]
            },
            {
                "DIAGNOSIS": [
                    0.835,
                    "mellitus",
                    [
                        38,
                        46
                    ]
                ]
            },
            {
                "DIAGNOSIS": [
                    0.985,
                    "Chronic",
                    [
                        77,
                        84
                    ]
                ]
            },
            {
                "DIAGNOSIS": [
                    0.995,
                    "kidney",
                    [
                        85,
                        91
                    ]
                ]
            },
            {
                "DIAGNOSIS": [
                    0.995,
                    "disease",
                    [
                        92,
                        99
                    ]
                ]
            },
            {
                "DIAGNOSIS": [
                    0.88,
                    ",",
                    [
                        99,
                        100
                    ]
                ]
            },
            {
                "DIAGNOSIS": [
                    0.976,
                    "stage",
                    [
                        101,
                        106
                    ]
                ]
            },
            {
                "DIAGNOSIS": [
                    0.953,
                    "III",
                    [
                        107,
                        110
                    ]
                ]
            },
            {
                "DIAGNOSIS": [
                    0.881,
                    "Sweet",
                    [
                        117,
                        122
                    ]
                ]
            },
            {
                "DIAGNOSIS": [
                    0.934,
                    "syndrome",
                    [
                        123,
                        131
                    ]
                ]
            },
            {
                "DIAGNOSIS": [
                    0.985,
                    "Hypertension",
                    [
                        138,
                        150
                    ]
                ]
            },
            {
                "DIAGNOSIS": [
                    0.945,
                    "Dyslipidemia",
                    [
                        157,
                        169
                    ]
                ]
            },
            {
                "DIAGNOSIS": [
                    0.932,
                    "Osteoporosis",
                    [
                        176,
                        188
                    ]
                ]
            },
            {
                "DIAGNOSIS": [
                    0.871,
                    "Anemia",
                    [
                        195,
                        201
                    ]
                ]
            },
            {
                "DIAGNOSIS": [
                    0.506,
                    "25-hydroxy-vitamin",
                    [
                        210,
                        228
                    ]
                ]
            },
            {
                "DIAGNOSIS": [
                    0.568,
                    "D",
                    [
                        229,
                        230
                    ]
                ]
            },
            {
                "DIAGNOSIS": [
                    0.61,
                    "deficiency",
                    [
                        231,
                        241
                    ]
                ]
            },
            {
                "DIAGNOSIS": [
                    0.898,
                    "Peripheral",
                    [
                        248,
                        258
                    ]
                ]
            },
            {
                "DIAGNOSIS": [
                    0.807,
                    "neuropathy",
                    [
                        259,
                        269
                    ]
                ]
            },
            {
                "DIAGNOSIS": [
                    0.963,
                    "Hypothyroidism",
                    [
                        306,
                        320
                    ]
                ]
            },
            {
                "DIAGNOSIS": [
                    0.969,
                    "Diabetic",
                    [
                        328,
                        336
                    ]
                ]
            },
            {
                "DIAGNOSIS": [
                    0.971,
                    "retinopathy",
                    [
                        337,
                        348
                    ]
                ]
            },
            {
                "DIAGNOSIS": [
                    0.939,
                    "diabetes",
                    [
                        467,
                        475
                    ]
                ]
            },
            {
                "DIAGNOSIS": [
                    0.963,
                    "kidney",
                    [
                        480,
                        486
                    ]
                ]
            },
            {
                "DIAGNOSIS": [
                    0.914,
                    "disease",
                    [
                        487,
                        494
                    ]
                ]
            },
            {
                "DIAGNOSIS": [
                    0.826,
                    "management",
                    [
                        495,
                        505
                    ]
                ]
            },
            {
                "DIAGNOSIS": [
                    0.442,
                    "variability",
                    [
                        631,
                        642
                    ]
                ]
            },
            {
                "PROBLEM": [
                    0.392,
                    "glucose",
                    [
                        650,
                        657
                    ]
                ]
            },
            {
                "DIAGNOSIS": [
                    0.369,
                    "control",
                    [
                        658,
                        665
                    ]
                ]
            },
            {
                "PROBLEM": [
                    0.456,
                    "upper",
                    [
                        688,
                        693
                    ]
                ]
            },
            {
                "PROBLEM": [
                    0.38,
                    "lower",
                    [
                        698,
                        703
                    ]
                ]
            },
            {
                "DIAGNOSIS": [
                    0.517,
                    "respiratory",
                    [
                        704,
                        715
                    ]
                ]
            },
            {
                "DIAGNOSIS": [
                    0.469,
                    "illnesses",
                    [
                        716,
                        725
                    ]
                ]
            },
            {
                "DIAGNOSIS": [
                    0.448,
                    "difficulties",
                    [
                        865,
                        877
                    ]
                ]
            },
            {
                "DIAGNOSIS": [
                    0.707,
                    "control",
                    [
                        1379,
                        1386
                    ]
                ]
            },
            {
                "PROBLEM": [
                    0.613,
                    "nausea",
                    [
                        2302,
                        2308
                    ]
                ]
            },
            {
                "PROBLEM": [
                    0.451,
                    "battery",
                    [
                        4380,
                        4387
                    ]
                ]
            }
        ],
        "average_entropy": 0.093,
        "uncertain_token_count": 18,
        "narrow_band_ratio": 0.019,
        "uncertain_tokens": {
            "DIAGNOSIS": [
                [
                    0.506,
                    "25-hydroxy-vitamin",
                    [
                        210,
                        228
                    ]
                ],
                [
                    0.442,
                    "variability",
                    [
                        631,
                        642
                    ]
                ],
                [
                    0.369,
                    "control",
                    [
                        658,
                        665
                    ]
                ],
                [
                    0.517,
                    "respiratory",
                    [
                        704,
                        715
                    ]
                ],
                [
                    0.469,
                    "illnesses",
                    [
                        716,
                        725
                    ]
                ],
                [
                    0.448,
                    "difficulties",
                    [
                        865,
                        877
                    ]
                ]
            ],
            "NA": [
                [
                    0.442,
                    "manifested",
                    [
                        270,
                        280
                    ]
                ],
                [
                    0.398,
                    "insensate",
                    [
                        284,
                        293
                    ]
                ],
                [
                    0.414,
                    "feet",
                    [
                        294,
                        298
                    ]
                ],
                [
                    0.422,
                    "in",
                    [
                        643,
                        645
                    ]
                ],
                [
                    0.445,
                    "her",
                    [
                        646,
                        649
                    ]
                ],
                [
                    0.517,
                    "recent",
                    [
                        681,
                        687
                    ]
                ],
                [
                    0.504,
                    "respiratory",
                    [
                        2220,
                        2231
                    ]
                ],
                [
                    0.425,
                    "hesitancy",
                    [
                        2478,
                        2487
                    ]
                ]
            ],
            "PROBLEM": [
                [
                    0.392,
                    "glucose",
                    [
                        650,
                        657
                    ]
                ],
                [
                    0.456,
                    "upper",
                    [
                        688,
                        693
                    ]
                ],
                [
                    0.38,
                    "lower",
                    [
                        698,
                        703
                    ]
                ],
                [
                    0.451,
                    "battery",
                    [
                        4380,
                        4387
                    ]
                ]
            ]
        },
        "narrow_band_width": 0.2
    }
}