{
    "file": "blood-in-toilet.txt-clean.txt",
    "lab_summary": [
        {
            "LAB": [
                0.901,
                "CBC",
                [
                    2081,
                    2084
                ]
            ]
        },
        {
            "LAB_VALUE": [
                0.571,
                "normal",
                [
                    2105,
                    2111
                ]
            ]
        },
        {
            "LAB": [
                0.78,
                "H",
                [
                    2155,
                    2156
                ]
            ]
        },
        {
            "LAB": [
                0.87,
                "H",
                [
                    2161,
                    2162
                ]
            ]
        },
        {
            "LAB_VALUE": [
                0.996,
                "14",
                [
                    2166,
                    2168
                ]
            ]
        },
        {
            "LAB_VALUE": [
                0.979,
                "42",
                [
                    2173,
                    2175
                ]
            ]
        },
        {
            "LAB": [
                0.951,
                "%",
                [
                    2175,
                    2176
                ]
            ]
        },
        {
            "LAB": [
                0.966,
                "CMP",
                [
                    2178,
                    2181
                ]
            ]
        },
        {
            "LAB_VALUE": [
                0.772,
                "normal",
                [
                    2194,
                    2200
                ]
            ]
        },
        {
            "LAB": [
                0.994,
                "PTT",
                [
                    2209,
                    2212
                ]
            ]
        },
        {
            "LAB": [
                0.955,
                "PT",
                [
                    2214,
                    2216
                ]
            ]
        },
        {
            "LAB": [
                0.95,
                "INR",
                [
                    2222,
                    2225
                ]
            ]
        },
        {
            "LAB_VALUE": [
                0.816,
                "normal",
                [
                    2231,
                    2237
                ]
            ]
        }
    ],
    "lab_uncertainty": {
        "average_entropy": 0.017,
        "uncertain_count": 1,
        "narrow_band_ratio": 0.002,
        "uncertain_tokens": {
            "LAB_VALUE": [
                [
                    0.571,
                    "normal",
                    [
                        2105,
                        2111
                    ]
                ]
            ]
        },
        "narrow_band_width": 0.4
    }
}